phytospatial/__init__.py
phytospatial/extract.py
phytospatial/loaders.py
phytospatial/vector.py
phytospatial/raster/__init__.py
phytospatial/raster/engine.py
phytospatial/raster/geom.py
phytospatial/raster/io.py
phytospatial/raster/layer.py
phytospatial/raster/partition.py
phytospatial/raster/resources.py
phytospatial/raster/utils.py
phytospatial-0.4.0.dist-info/licenses/NOTICE
phytospatial-0.4.0.dist-info/METADATA
phytospatial-0.4.0.dist-info/WHEEL
phytospatial-0.4.0.dist-info/top_level.txt
phytospatial-0.4.0.dist-info/RECORD
