Metadata-Version: 2.4
Name: phytospatial
Version: 0.4.0
Summary: A python package that processes lidar and imagery data in forestry
Author-email: Louis-Vincent Grand'Maison <lvgra@ulaval.ca>
License-Expression: Apache-2.0
Project-URL: Homepage, https://github.com/Louis-Gm/phytospatial
Project-URL: Bug Tracker, https://github.com/Louis-Gm/phytospatial/issues
Keywords: forestry,remote sensing,imagery,image processing,geospatial,GIS
Classifier: Development Status :: 4 - Beta
Classifier: Intended Audience :: Science/Research
Classifier: Topic :: Scientific/Engineering :: Image Processing
Classifier: Topic :: Scientific/Engineering :: GIS
Classifier: Programming Language :: Python :: 3.10
Classifier: Operating System :: OS Independent
Requires-Python: >=3.10
License-File: NOTICE
Requires-Dist: geopandas
Requires-Dist: pandas
Requires-Dist: tqdm
Requires-Dist: rasterio>=1.4
Requires-Dist: numpy>=1.24
Requires-Dist: psutil
Provides-Extra: analysis
Requires-Dist: pyarrow>=10.0; extra == "analysis"
Requires-Dist: scikit-learn; extra == "analysis"
Requires-Dist: scipy; extra == "analysis"
Provides-Extra: docs
Requires-Dist: mkdocs>=1.5; extra == "docs"
Requires-Dist: mkdocs-material>=9.5; extra == "docs"
Requires-Dist: mkdocstrings[python]>=0.24; extra == "docs"
Requires-Dist: mkdocs-include-markdown-plugin>=4.0; extra == "docs"
Requires-Dist: mkdocs-jupyter>=0.24; extra == "docs"
Provides-Extra: dev
Requires-Dist: pytest; extra == "dev"
Requires-Dist: build; extra == "dev"
Requires-Dist: twine; extra == "dev"
Requires-Dist: pre-commit; extra == "dev"
Requires-Dist: black; extra == "dev"
Requires-Dist: memory_profiler; extra == "dev"
Requires-Dist: ruff; extra == "dev"
Dynamic: license-file
